data/1471-2180-11-174.nxml
data/1472-6831-8-11.nxml
data/6605965a.nxml
data/ehp-116-1694.nxml
data/mds526.nxml
data/pmids.txt
data/pntd.0002065.nxml
data/pone.0000217.nxml
data/pone.0046493.nxml
data/pubmed-29768149.xml
data/pubmed20n0014.xml.gz
data/pubmed21n1298.xml.gz
docs/Makefile
docs/README.md
docs/api.rst
docs/conf.py
docs/index.rst
docs/install.rst
docs/make.bat
docs/resources.rst
docs/spark.rst
paper/paper.bib
paper/paper.md
pubmed_parser/__init__.py
pubmed_parser/medline_parser.py
pubmed_parser/pubmed_oa_parser.py
pubmed_parser/pubmed_web_parser.py
pubmed_parser/utils.py
scripts/README.md
scripts/medline_spark.py
scripts/pubmed_oa_spark.py
scripts/utils.py
tests/__init__.py
tests/test_medline_parser.py
tests/test_pubmed_oa_parser.py
tests/test_pubmed_web_parser.py
pubmed_parser-0.5.1.dist-info/LICENSE
pubmed_parser-0.5.1.dist-info/METADATA
pubmed_parser-0.5.1.dist-info/WHEEL
pubmed_parser-0.5.1.dist-info/top_level.txt
pubmed_parser-0.5.1.dist-info/RECORD
