Metadata-Version: 2.1
Name: pubmed_parser
Version: 0.5.1
Summary: A python parser for Pubmed Open-Access Subset and MEDLINE XML repository
Author-email: Titipat Achakulvisut <my.titipat@gmail.com>
Maintainer-email: Titipat Achakulvisut <my.titipat@gmail.com>, "Michael E. Rose" <Michael.Ernst.Rose@gmail.com>
License: MIT (c) 2015 - 2024 Titipat Achakulvisut, Daniel E. Acuna
Project-URL: homepage, https://github.com/titipata/pubmed_parser
Project-URL: download, https://github.com/titipata/pubmed_parser.git
Project-URL: documentation, http://titipata.github.io/pubmed_parser
Project-URL: bug_tracker, https://github.com/titipata/pubmed_parser/issues
Keywords: Python,MEDLINE,PubMed,Biomedical corpus,Natural Language Processing
Classifier: Intended Audience :: Science/Research
Classifier: Intended Audience :: Developers
Classifier: License :: OSI Approved :: MIT License
Classifier: Programming Language :: Python
Classifier: Natural Language :: English
Classifier: Topic :: Software Development
Classifier: Topic :: Software Development :: Libraries :: Python Modules
Classifier: Topic :: Scientific/Engineering
Classifier: Topic :: Scientific/Engineering :: Information Analysis
Classifier: Operating System :: Microsoft :: Windows
Classifier: Operating System :: Unix
Classifier: Operating System :: MacOS
Classifier: Programming Language :: Python :: 3.6
Classifier: Programming Language :: Python :: 3.7
Classifier: Programming Language :: Python :: 3.8
Classifier: Programming Language :: Python :: 3.9
Classifier: Programming Language :: Python :: 3.10
Classifier: Programming Language :: Python :: 3.11
License-File: LICENSE
Requires-Dist: lxml
Requires-Dist: unidecode
Requires-Dist: requests
Requires-Dist: six
Requires-Dist: numpy
Provides-Extra: docs
Requires-Dist: sphinx; extra == "docs"
Requires-Dist: sphinx-rtd-theme; extra == "docs"
Requires-Dist: sphinx-gallery; extra == "docs"
Provides-Extra: tests
Requires-Dist: pytest; extra == "tests"
Requires-Dist: pytest-cov; extra == "tests"
